ipycalc/__init__.py
ipycalc/calc.py
ipycalc/constants_en.txt
ipycalc/ipycalc_en.txt
ipycalc/nbconvert_template/base.html.j2
ipycalc/nbconvert_template/cell_id_anchor.j2
ipycalc/nbconvert_template/celltags.j2
ipycalc/nbconvert_template/config.json
ipycalc/nbconvert_template/display_priority.j2
ipycalc/nbconvert_template/index.html.j2
ipycalc/nbconvert_template/jupyter_widgets.html.j2
ipycalc/nbconvert_template/mathjax.html.j2
ipycalc/nbconvert_template/mermaidjs.html.j2
ipycalc/nbconvert_template/null.j2
ipycalc/nbconvert_template/static/index.css
ipycalc/nbconvert_template/static/ipycalc.css
ipycalc/nbconvert_template/static/theme-dark.css
ipycalc/nbconvert_template/static/theme-light.css
ipycalc-0.0.75.dist-info/licenses/LICENSE
ipycalc-0.0.75.dist-info/METADATA
ipycalc-0.0.75.dist-info/WHEEL
ipycalc-0.0.75.dist-info/entry_points.txt
ipycalc-0.0.75.dist-info/top_level.txt
ipycalc-0.0.75.dist-info/RECORD
