Metadata-Version: 2.4
Name: ipycalc
Version: 0.0.75
Summary: Clean looking engineering calculations for IPython
Home-page: https://github.com/JWock82/ipycalc.git
Author: D. Craig Brinck, PE, SE
Author-email: Building.Code@outlook.com
Classifier: Programming Language :: Python :: 3
Classifier: License :: OSI Approved :: MIT License
Classifier: Operating System :: OS Independent
License-File: LICENSE
Requires-Dist: jupyterlab
Requires-Dist: nbconvert>=6.0
Dynamic: author
Dynamic: author-email
Dynamic: classifier
Dynamic: description
Dynamic: description-content-type
Dynamic: home-page
Dynamic: license-file
Dynamic: requires-dist
Dynamic: summary
